[
  {
    "id": "1001",
    "name": "BLR Commuter",
    "username": "BengaluruCommuter",
    "created_at": "2018-03-15T12:00:00Z",
    "description": "Navigating the streets of Bengaluru one traffic jam at a time. Lover of good roads and short commutes.",
    "profile_image_url": "https://example.com/profile_images/commuter.png",
    "protected": false,
    "url": "",
    "verified": false
  },
  {
    "id": "1002",
    "name": "Kavya R.",
    "username": "CoffeeLoverBLR",
    "created_at": "2020-09-22T08:30:00Z",
    "description": "Exploring Bangalore's cafe scene, one filter coffee at a time. ☕",
    "profile_image_url": "https://example.com/profile_images/coffeelover.png",
    "protected": false,
    "url": "https://coffeeblr.com",
    "verified": false
  },
  {
    "id": "1003",
    "name": "Bangalore Foodie",
    "username": "BLRFoodie",
    "created_at": "2017-11-05T18:45:00Z",
    "description": "On a mission to find the best food and brews in Bengaluru. From craft beer to crispy dosas.",
    "profile_image_url": "https://example.com/profile_images/foodie.png",
    "protected": false,
    "url": "",
    "verified": false
  },
  {
    "id": "1004",
    "name": "Aditya Sharma",
    "username": "TechEnthusiast",
    "created_at": "2019-05-19T14:20:00Z",
    "description": "Software Engineer based in Electronic City. Passionate about AI, startups, and all things tech in India's Silicon Valley.",
    "profile_image_url": "https://example.com/profile_images/techenthusiast.png",
    "protected": false,
    "url": "https://github.com/adityasharma",
    "verified": false
  },
  {
    "id": "1005",
    "name": "Prakash Photography",
    "username": "BLRPhotographer",
    "created_at": "2016-08-12T09:00:00Z",
    "description": "Capturing the beauty of Bangalore and its surroundings, from sunsets at Nandi Hills to the bustling city life.",
    "profile_image_url": "https://example.com/profile_images/photographer.png",
    "protected": false,
    "url": "https://prakashphotos.com",
    "verified": false
  },
  {
    "id": "1006",
    "name": "Ananya Desai",
    "username": "ArtLoverBLR",
    "created_at": "2021-02-28T11:55:00Z",
    "description": "Discovering the thriving art scene of Bengaluru, from street murals to gallery exhibitions.",
    "profile_image_url": "https://example.com/profile_images/artlover.png",
    "protected": false,
    "url": "",
    "verified": false
  },
  {
    "id": "1007",
    "name": "BLR Weather Updates",
    "username": "BLRWeatherUpdate",
    "created_at": "2019-07-01T07:00:00Z",
    "description": "Your unofficial source for real-time weather alerts and forecasts for the Bengaluru area. Stay safe!",
    "profile_image_url": "https://example.com/profile_images/weather.png",
    "protected": false,
    "url": "",
    "verified": false
  },
  {
    "id": "1008",
    "name": "Rohan",
    "username": "WeekendExplorer",
    "created_at": "2022-04-10T16:10:00Z",
    "description": "Making the most of weekends in and around Bangalore. Parks, food crawls, and everything in between.",
    "profile_image_url": "https://example.com/profile_images/explorer.png",
    "protected": false,
    "url": "",
    "verified": false
  },
  {
    "id": "1009",
    "name": "Startup Guru",
    "username": "StartupGuru",
    "created_at": "2015-10-30T19:00:00Z",
    "description": "Mentor and Angel Investor in the Bangalore startup ecosystem. Always looking for the next big thing.",
    "profile_image_url": "https://example.com/profile_images/startupguru.png",
    "protected": false,
    "url": "https://startupblr.vc",
    "verified": false
  },
  {
    "id": "3001",
    "name": "BBMP",
    "username": "BBMP_Official",
    "created_at": "2012-01-10T10:00:00Z",
    "description": "Official account of the Bruhat Bengaluru Mahanagara Palike. Updates on city infrastructure, public advisories, and civic services.",
    "profile_image_url": "https://example.com/profile_images/bbmp.png",
    "protected": false,
    "url": "https://bbmp.gov.in",
    "verified": true
  },
  {
    "id": "3002",
    "name": "Bengaluru City Police",
    "username": "BlrCityPolice",
    "created_at": "2011-05-20T11:30:00Z",
    "description": "Official account of the Bengaluru City Police. Traffic advisories, public safety announcements, and crime alerts.",
    "profile_image_url": "https://example.com/profile_images/blrpolice.png",
    "protected": false,
    "url": "https://bcp.gov.in",
    "verified": true
  },
  {
    "id": "1010",
    "name": "Alex",
    "username": "GlobalNomad",
    "created_at": "2021-11-15T22:00:00Z",
    "description": "Traveling the world, one city at a time. Currently exploring the Garden City!",
    "profile_image_url": "https://example.com/profile_images/nomad.png",
    "protected": false,
    "url": "https://globalnomad.blog",
    "verified": false
  },
  {
    "id": "1011",
    "name": "Sanjana Patel",
    "username": "UrbanPlannerBLR",
    "created_at": "2018-06-25T14:00:00Z",
    "description": "Urban Planner focused on sustainable public transport and infrastructure development in Bengaluru. #NammaMetro",
    "profile_image_url": "https://example.com/profile_images/planner.png",
    "protected": false,
    "url": "",
    "verified": false
  },
  {
    "id": "1012",
    "name": "Food Explorer",
    "username": "FoodExplorer",
    "created_at": "2020-02-18T19:30:00Z",
    "description": "From VV Puram street food to high-end restaurants, I'm on a quest to taste it all.",
    "profile_image_url": "https://example.com/profile_images/foodexplorer.png",
    "protected": false,
    "url": "",
    "verified": false
  },
  {
    "id": "1013",
    "name": "Dr. Arjun Verma",
    "username": "AIResearcher",
    "created_at": "2019-01-09T17:00:00Z",
    "description": "AI Researcher and academic. Fascinated by the intersection of technology and society in Bangalore.",
    "profile_image_url": "https://example.com/profile_images/researcher.png",
    "protected": false,
    "url": "https://bengaluruai.institute/averma",
    "verified": false
  },
  {
    "id": "1014",
    "name": "Vikram Singh",
    "username": "FitnessFanatic",
    "created_at": "2021-08-01T06:00:00Z",
    "description": "Fitness enthusiast. You can find me running in Lalbagh or Cubbon Park every morning.",
    "profile_image_url": "https://example.com/profile_images/fitness.png",
    "protected": false,
    "url": "",
    "verified": false
  },
  {
    "id": "1015",
    "name": "Music Explorer",
    "username": "MusicExplorer",
    "created_at": "2019-03-12T23:00:00Z",
    "description": "Exploring Bangalore's diverse music scene, from indie bands to classical concerts.",
    "profile_image_url": "https://example.com/profile_images/music.png",
    "protected": false,
    "url": "",
    "verified": false
  },
  {
    "id": "1016",
    "name": "Priya Menon",
    "username": "StartupObserver",
    "created_at": "2016-12-05T15:15:00Z",
    "description": "Journalist covering the Bangalore startup ecosystem for a leading tech publication. #InnovationHub",
    "profile_image_url": "https://example.com/profile_images/observer.png",
    "protected": false,
    "url": "",
    "verified": false
  },
  {
    "id": "1017",
    "name": "Cafe Hopper BLR",
    "username": "CafeHopperBLR",
    "created_at": "2022-01-20T13:00:00Z",
    "description": "Hopping from one cafe to another in Bangalore. Reviewing coffee, ambiance, and everything in between.",
    "profile_image_url": "https://example.com/profile_images/cafehopper.png",
    "protected": false,
    "url": "",
    "verified": false
  },
  {
    "id": "1018",
    "name": "Nature Lover BLR",
    "username": "NatureLoverBLR",
    "created_at": "2018-09-14T09:45:00Z",
    "description": "Advocate for protecting Bangalore's green spaces and lakes. #GardenCity",
    "profile_image_url": "https://example.com/profile_images/naturelover.png",
    "protected": false,
    "url": "",
    "verified": false
  },
  {
    "id": "1019",
    "name": "Event Goer BLR",
    "username": "EventGoerBLR",
    "created_at": "2021-06-11T20:00:00Z",
    "description": "Always on the lookout for exciting events in Bangalore, from Comic Con to literature festivals.",
    "profile_image_url": "https://example.com/profile_images/eventgoer.png",
    "protected": false,
    "url": "",
    "verified": false
  },
  {
    "id": "1020",
    "name": "Tech Recruiter BLR",
    "username": "TechRecruiterBLR",
    "created_at": "2017-04-02T10:10:00Z",
    "description": "Connecting top tech talent with innovative startups in Bangalore. #GlobalTalent",
    "profile_image_url": "https://example.com/profile_images/recruiter.png",
    "protected": false,
    "url": "https://linkedin.com/in/techrecruiterblr",
    "verified": false
  },
  {
    "id": "1023",
    "name": "Bookworm BLR",
    "username": "BookwormBLR",
    "created_at": "2019-08-08T18:00:00Z",
    "description": "Discovering hidden gem bookstores and literary events in Bangalore. #BangaloreReads",
    "profile_image_url": "https://example.com/profile_images/bookworm.png",
    "protected": false,
    "url": "",
    "verified": false
  },
  {
    "id": "1024",
    "name": "Isha Singh",
    "username": "FounderLife",
    "created_at": "2020-11-30T21:00:00Z",
    "description": "Founder of a tech startup in Bangalore. Sharing the journey, the highs and the lows. #StartupLife",
    "profile_image_url": "https://example.com/profile_images/founder.png",
    "protected": false,
    "url": "https://mycoolstartup.io",
    "verified": false
  },
  {
    "id": "1025",
    "name": "Peace Seeker BLR",
    "username": "PeaceSeekerBLR",
    "created_at": "2022-03-05T07:30:00Z",
    "description": "Finding serene spots for morning walks and tranquility amidst the city's hustle.",
    "profile_image_url": "https://example.com/profile_images/peaceseeker.png",
    "protected": false,
    "url": "",
    "verified": false
  },
  {
    "id": "2001",
    "name": "Frustrated Commuter",
    "username": "FrustratedCommuter",
    "created_at": "2022-05-20T19:00:00Z",
    "description": "My daily battle with Bangalore's traffic. It's a test of patience. #TrafficNightmare",
    "profile_image_url": "https://example.com/profile_images/frustrated.png",
    "protected": false,
    "url": "",
    "verified": false
  },
  {
    "id": "2002",
    "name": "Clean Air Advocate",
    "username": "CleanAirAdvocate",
    "created_at": "2019-12-01T11:00:00Z",
    "description": "Advocating for better air quality and a cleaner environment in Bengaluru. #Pollution",
    "profile_image_url": "https://example.com/profile_images/cleanair.png",
    "protected": false,
    "url": "",
    "verified": false
  },
  {
    "id": "2003",
    "name": "Road Rage BLR",
    "username": "RoadRageBLR",
    "created_at": "2021-10-10T09:00:00Z",
    "description": "Documenting my daily adventures with Bangalore's potholes and questionable road infrastructure.",
    "profile_image_url": "https://example.com/profile_images/roadrage.png",
    "protected": false,
    "url": "",
    "verified": false
  },
  {
    "id": "2004",
    "name": "WFH BLR",
    "username": "WorkFromHomeBLR",
    "created_at": "2020-04-01T10:00:00Z",
    "description": "Trying to maintain productivity through Bangalore's daily power cuts. #WFHProblems",
    "profile_image_url": "https://example.com/profile_images/wfh.png",
    "protected": false,
    "url": "",
    "verified": false
  },
  {
    "id": "2005",
    "name": "Budget Watcher",
    "username": "BudgetWatcher",
    "created_at": "2018-07-15T13:30:00Z",
    "description": "Keeping an eye on the rising cost of living in Bangalore. Sharing tips for budget-friendly living.",
    "profile_image_url": "https://example.com/profile_images/budget.png",
    "protected": false,
    "url": "",
    "verified": false
  },
  {
    "id": "2006",
    "name": "Water Warrior",
    "username": "WaterWarrior",
    "created_at": "2017-02-20T16:00:00Z",
    "description": "Raising awareness about water scarcity and the need for conservation in Bengaluru. #WaterCrisis",
    "profile_image_url": "https://example.com/profile_images/water.png",
    "protected": false,
    "url": "",
    "verified": false
  },
  {
    "id": "2007",
    "name": "Quiet Seeker",
    "username": "QuietSeeker",
    "created_at": "2022-06-05T22:00:00Z",
    "description": "In search of peace and quiet amidst the noise pollution of the city.",
    "profile_image_url": "https://example.com/profile_images/quiet.png",
    "protected": false,
    "url": "",
    "verified": false
  },
  {
    "id": "2008",
    "name": "Transit Advocate",
    "username": "TransitAdvocate",
    "created_at": "2019-11-18T08:45:00Z",
    "description": "Pushing for better, more reliable public transport options in Bangalore. #PublicTransportBLR",
    "profile_image_url": "https://example.com/profile_images/transit.png",
    "protected": false,
    "url": "",
    "verified": false
  },
  {
    "id": "2009",
    "name": "City Planner",
    "username": "CityPlanner",
    "created_at": "2016-03-22T14:30:00Z",
    "description": "Urban planning professional with a focus on sustainable development for a growing Bangalore.",
    "profile_image_url": "https://example.com/profile_images/cityplanner.png",
    "protected": false,
    "url": "https://linkedin.com/in/cityplannerblr",
    "verified": false
  },
  {
    "id": "2010",
    "name": "Green Citizen",
    "username": "GreenCitizen",
    "created_at": "2020-08-30T12:00:00Z",
    "description": "Passionate about waste management, recycling, and keeping Bengaluru clean. #CleanBLR",
    "profile_image_url": "https://example.com/profile_images/green.png",
    "protected": false,
    "url": "",
    "verified": false
  }
]